setup.py
pypdfml/__init__.py
pypdfml/pypdfml.py
pypdfml.egg-info/PKG-INFO
pypdfml.egg-info/SOURCES.txt
pypdfml.egg-info/dependency_links.txt
pypdfml.egg-info/requires.txt
pypdfml.egg-info/top_level.txt