Metadata-Version: 1.0
Name: pypdfml
Version: 0.1.0alpha
Summary: Simple XML wrapper for reportlab.
Home-page: https://github.com/badzong/pypdfml
Author: Manuel Badzong
Author-email: manuel@andev.ch
License: unknown
Keywords: pdf generating reportlab report xml jinja
Platform: UNKNOWN
